rabbit_clients/__init__.py
rabbit_clients/clients/__init__.py
rabbit_clients/clients/blocking.py
rabbit_clients/clients/config.py
tests/__init__.py
tests/conftest.py
tests/test_base.py
rabbit_clients-3.0.0.dist-info/LICENSE.txt
rabbit_clients-3.0.0.dist-info/METADATA
rabbit_clients-3.0.0.dist-info/WHEEL
rabbit_clients-3.0.0.dist-info/top_level.txt
rabbit_clients-3.0.0.dist-info/RECORD
